{
  "annotations": {
    "list": [

    ]
  },
  "description": "",
  "editable": true,
  "fiscalYearStartMonth": 0,
  "graphTooltip": 1,
  "id": null,
  "links": [

  ],
  "panels": [
    {
      "id": 1,
      "type": "row",
      "title": "pods",
      "gridPos": {
        "h": 1,
        "w": 24,
        "x": 0,
        "y": 0
      },
      "collapsed": false,
      "panels": [

      ]
    },
    {
      "id": 2,
      "title": "Pods",
      "type": "stat",
      "gridPos": {
        "h": 8,
        "w": 6,
        "x": 0,
        "y": 1
      },
      "targets": [
        {
          "refId": "A",
          "expr": "count(kube_pod_info{namespace=\"$namespace\"})",
          "datasource": {
            "type": "prometheus",
            "uid": "vm"
          }
        }
      ],
      "fieldConfig": {
        "defaults": {
        },
        "overrides": [

        ]
      },
      "options": {
        "reduceOptions": {
          "calcs": [
            "lastNotNull"
          ],
          "fields": "",
          "values": false
        },
        "textMode": "auto"
      }
    },
    {
      "id": 3,
      "title": "Pod CPU",
      "type": "timeseries",
      "gridPos": {
        "h": 8,
        "w": 12,
        "x": 6,
        "y": 1
      },
      "targets": [
        {
          "refId": "A",
          "expr": "sum by (pod) (rate(container_cpu_usage_seconds_total{namespace=\"$namespace\"}[5m])) * 100",
          "datasource": {
            "type": "prometheus",
            "uid": "vm"
          },
          "legendFormat": "{{pod}}"
        }
      ],
      "fieldConfig": {
        "defaults": {
          "unit": "percent",
          "custom": {
            "fillOpacity": 10,
            "lineWidth": 2
          }
        },
        "overrides": [

        ]
      },
      "options": {
        "tooltip": {
          "mode": "multi",
          "sort": "none"
        },
        "legend": {
          "displayMode": "list",
          "placement": "bottom"
        }
      }
    },
    {
      "id": 4,
      "title": "Pod memory",
      "type": "timeseries",
      "gridPos": {
        "h": 8,
        "w": 12,
        "x": 0,
        "y": 9
      },
      "targets": [
        {
          "refId": "A",
          "expr": "sum by (pod) (container_memory_working_set_bytes{namespace=\"$namespace\"})",
          "datasource": {
            "type": "prometheus",
            "uid": "vm"
          },
          "legendFormat": "{{pod}}"
        }
      ],
      "fieldConfig": {
        "defaults": {
          "unit": "bytes",
          "custom": {
            "fillOpacity": 10,
            "lineWidth": 2
          }
        },
        "overrides": [

        ]
      },
      "options": {
        "tooltip": {
          "mode": "multi",
          "sort": "none"
        },
        "legend": {
          "displayMode": "list",
          "placement": "bottom"
        }
      }
    },
    {
      "id": 5,
      "title": "Restarts (1h)",
      "type": "stat",
      "gridPos": {
        "h": 8,
        "w": 6,
        "x": 12,
        "y": 9
      },
      "targets": [
        {
          "refId": "A",
          "expr": "sum(increase(kube_pod_container_status_restarts_total{namespace=\"$namespace\"}[1h]))",
          "datasource": {
            "type": "prometheus",
            "uid": "vm"
          }
        }
      ],
      "fieldConfig": {
        "defaults": {
          "thresholds": {
            "mode": "absolute",
            "steps": [
              {
                "color": "green",
                "value": null
              },
              {
                "color": "yellow",
                "value": 3.0
              },
              {
                "color": "red",
                "value": 10.0
              }
            ]
          }
        },
        "overrides": [

        ]
      },
      "options": {
        "reduceOptions": {
          "calcs": [
            "lastNotNull"
          ],
          "fields": "",
          "values": false
        },
        "textMode": "auto"
      }
    },
    {
      "id": 6,
      "type": "row",
      "title": "nodes",
      "gridPos": {
        "h": 1,
        "w": 24,
        "x": 0,
        "y": 17
      },
      "collapsed": false,
      "panels": [

      ]
    },
    {
      "id": 7,
      "title": "Nodes",
      "type": "stat",
      "gridPos": {
        "h": 8,
        "w": 6,
        "x": 0,
        "y": 18
      },
      "targets": [
        {
          "refId": "A",
          "expr": "count(kube_node_info)",
          "datasource": {
            "type": "prometheus",
            "uid": "vm"
          }
        }
      ],
      "fieldConfig": {
        "defaults": {
        },
        "overrides": [

        ]
      },
      "options": {
        "reduceOptions": {
          "calcs": [
            "lastNotNull"
          ],
          "fields": "",
          "values": false
        },
        "textMode": "auto"
      }
    },
    {
      "id": 8,
      "title": "Ready",
      "type": "stat",
      "gridPos": {
        "h": 8,
        "w": 6,
        "x": 6,
        "y": 18
      },
      "targets": [
        {
          "refId": "A",
          "expr": "count(kube_node_status_condition{condition=\"Ready\",status=\"true\"})",
          "datasource": {
            "type": "prometheus",
            "uid": "vm"
          }
        }
      ],
      "fieldConfig": {
        "defaults": {
          "thresholds": {
            "mode": "absolute",
            "steps": [
              {
                "color": "red",
                "value": null
              },
              {
                "color": "green",
                "value": 1.0
              }
            ]
          }
        },
        "overrides": [

        ]
      },
      "options": {
        "reduceOptions": {
          "calcs": [
            "lastNotNull"
          ],
          "fields": "",
          "values": false
        },
        "textMode": "auto"
      }
    }
  ],
  "schemaVersion": 39,
  "tags": [
    "rio",
    "cluster",
    "overview"
  ],
  "templating": {
    "list": [
      {
        "datasource": {
          "type": "prometheus",
          "uid": null
        },
        "query": "label_values(kube_pod_info, namespace)",
        "refresh": 2,
        "sort": 1,
        "multi": true,
        "includeAll": true,
        "name": "namespace",
        "label": "Namespace",
        "type": "query",
        "hide": 0
      }
    ]
  },
  "time": {
    "from": "now-1h",
    "to": "now"
  },
  "timepicker": {
  },
  "timezone": "utc",
  "title": "rio · cluster overview",
  "uid": "rio-cluster-overview",
  "version": 1
}